crisp_ml/__init__.py
crisp_ml/autoencode.py
fuzzy_ml/__init__.py
fuzzy_ml/datasets.py
fuzzy_ml/fetchers.py
fuzzy_ml/utils.py
fuzzy_ml/association/__init__.py
fuzzy_ml/association/temporal.py
fuzzy_ml/clustering/__init__.py
fuzzy_ml/clustering/ecm.py
fuzzy_ml/clustering/empirical.py
fuzzy_ml/partitioning/__init__.py
fuzzy_ml/partitioning/clip.py
fuzzy_ml/partitioning/equal.py
fuzzy_ml/partitioning/meta.py
fuzzy_ml/partitioning/utils.py
fuzzy_ml/pruning/__init__.py
fuzzy_ml/pruning/rpy2/__init__.py
fuzzy_ml/pruning/rpy2/rough_theory.py
fuzzy_ml/rpy2/__init__.py
fuzzy_ml/rpy2/packages.py
fuzzy_ml/rulemaking/__init__.py
fuzzy_ml/rulemaking/common.py
fuzzy_ml/rulemaking/latent_lockstep.py
fuzzy_ml/rulemaking/wang_mendel.py
fuzzy_ml/summarization/__init__.py
fuzzy_ml/summarization/quantifiers.py
fuzzy_ml/summarization/query.py
fuzzy_ml/summarization/summary.py
fuzzy_ml-0.0.5.dist-info/METADATA
fuzzy_ml-0.0.5.dist-info/WHEEL
fuzzy_ml-0.0.5.dist-info/licenses/LICENSE
fuzzy_ml-0.0.5.dist-info/RECORD
