Metadata-Version: 2.4
Name: fuzzy-ml
Version: 0.0.5
Summary: Leverage fuzzy theory for machine learning. Perform quantitative temporal transaction analysis, linguistic summarization of data, etc.
Project-URL: Homepage, https://github.com/johnHostetter/fuzzy-ml
Project-URL: Issues, https://github.com/johnHostetter/fuzzy-ml/issues
Author-email: John Wesley Hostetter <jhostetter16@gmail.com>
License-File: LICENSE
Classifier: License :: OSI Approved :: MIT License
Classifier: Operating System :: OS Independent
Classifier: Programming Language :: Python :: 3
Requires-Python: >=3.9
